{
  "bebe-4c": 25,
  "bebe-el-comtat": 25,
  "bebe-mutxamel": 25,
  "bebe-taronger": 25,
  "bebe-xulilla": 25,
  "bordados-a-mano-assegador": 35,
  "bordados-a-mano-crevillent": 35,
  "bordados-a-mano-tollos": 35,
  "bordados-a-mano-tremcacaps": 35,
  "bordados-a-mano-trencacaps-esta": 35,
  "bordados-a-maquina-ador": 32,
  "bordados-a-maquina-canyar-brodades": 32,
  "bordados-a-maquina-clavellina": 32,
  "bordados-a-maquina-en": 32,
  "bordados-a-maquina-magnolia": 32,
  "colocados-ardalet": 30,
  "colocados-base-en": 30,
  "colocados-benicarlo": 30,
  "colocados-benimeli": 30,
  "colocados-caroig": 30,
  "colocados-fonteta": 30,
  "colocados-la-safor": 30,
  "colocados-la-senia": 30,
  "colocados-la-torre": 30,
  "colocados-los-cloticos": 30,
  "colocados-mimosa": 30,
  "colocados-olivera": 30,
  "colocados-pla-del-arc": 30,
  "colocados-taronger": 30,
  "colocados-xulilla": 30,
  "como-se-borda-camelia": 30,
  "como-se-borda-canyar-brodades": 30,
  "cuatro-colores-castalla": 30,
  "cuatro-colores-gerbera": 30,
  "cuatro-colores-olivera": 30,
  "cuatro-colores-pla-del-arc": 30,
  "dibujo-vertical-3-fonts": 30,
  "dibujo-vertical-5a": 30,
  "dibujo-vertical-alcocer": 30,
  "dibujo-vertical-alqueria": 30,
  "dibujo-vertical-amadorio": 30,
  "dos-colores-acacia": 30,
  "dos-colores-ador": 30,
  "dos-colores-agres": 30,
  "dos-colores-baix-maestrat": 30,
  "dos-colores-benicarlo": 30,
  "lisos-alberri": 20,
  "lisos-alt-del-porti": 20,
  "lisos-base": 20,
  "lisos-belluga": 20,
  "lisos-beniferri": 20,
  "lisos-benisaido": 20,
  "lisos-borriana": 20,
  "lisos-canyis": 20,
  "lisos-caudete": 20,
  "lisos-cigrons": 20,
  "rayados-3-fonts": 28,
  "rayados-acacia": 28,
  "rayados-ador": 28,
  "rayados-agres": 28,
  "rayados-alcocer": 28,
  "rayados-alqueria": 28,
  "rayados-amadorio": 28,
  "rayados-aspe": 28,
  "rayados-auro": 28,
  "rayados-avet": 28,
  "sin-calados-ador": 30,
  "sin-calados-beniali": 30,
  "sin-calados-benirrama": 30,
  "sin-calados-bugarra": 30,
  "sin-calados-carraixet": 30,
  "sin-calados-castalla": 30,
  "sin-calados-danses": 30,
  "sin-calados-els-llencols": 30,
  "sin-calados-gatova": 30,
  "sin-calados-irta": 30,
  "tres-colores-alqueria": 30,
  "tres-colores-auro": 30,
  "tres-colores-avet": 30,
  "tres-colores-bambu": 30,
  "tres-colores-beniali": 30,
  "tres-colores-benimarfull": 30,
  "tres-colores-benissiva": 30,
  "tres-colores-bussot": 30,
  "tres-colores-cabriel": 30,
  "tres-colores-castanyer": 30
}